odooku/__init__.py
odooku/api.py
odooku/logger.py
odooku/params.py
odooku/request.py
odooku/backends/__init__.py
odooku/backends/base.py
odooku/backends/redis/__init__.py
odooku/backends/redis/backend.py
odooku/backends/redis/session.py
odooku/backends/s3/__init__.py
odooku/backends/s3/backend.py
odooku/cli/__init__.py
odooku/cli/main.py
odooku/cli/resolve.py
odooku/helpers/__init__.py
odooku/helpers/debug.py
odooku/helpers/env.py
odooku/helpers/split.py
odooku/patch/__init__.py
odooku/patch/helpers.py
odooku/patch/patch.py
odooku/services/__init__.py
odooku/services/cron/__init__.py
odooku/services/cron/runner.py
odooku/services/websocket/__init__.py
odooku/services/websocket/application.py
odooku/services/websocket/channel.py
odooku/services/websocket/requests.py
odooku/services/websocket/server.py
odooku/services/wsgi/__init__.py
odooku/services/wsgi/rules.py
odooku/services/wsgi/server.py
odooku/tools/__init__.py
odooku/tools/lru.py
odooku_addons/__init__.py
odooku_addons/amazon_s3/__init__.py
odooku_addons/amazon_s3/__manifest__.py
odooku_addons/amazon_s3/models/__init__.py
odooku_addons/amazon_s3/models/ir_attachment.py
odooku_addons/amazon_s3/static/description/icon.png
odooku_addons/cdn/__init__.py
odooku_addons/cdn/__manifest__.py
odooku_addons/cdn/models/__init__.py
odooku_addons/cdn/models/ir_qweb.py
odooku_addons/websocket/__init__.py
odooku_addons/websocket/__manifest__.py
odooku_addons/websocket/models/__init__.py
odooku_addons/websocket/models/ir_qweb.py
odooku_addons/websocket/static/src/js/ajax.js
odooku_addons/websocket/static/src/js/ajax.original.js
odooku_addons/websocket/static/src/js/session.js
odooku_addons/websocket/static/src/js/websocket.js
odooku_addons/websocket/views/assets.xml
odooku_commands/__init__.py
odooku_commands/cdn.py
odooku_commands/cron.py
odooku_commands/database.py
odooku_commands/info.py
odooku_commands/runtests.py
odooku_commands/shell.py
odooku_commands/trans.py
odooku_commands/wsgi.py
odooku_patches/__init__.py
odooku-11.0.14.dist-info/LICENSE
odooku-11.0.14.dist-info/METADATA
odooku-11.0.14.dist-info/WHEEL
odooku-11.0.14.dist-info/entry_points.txt
odooku-11.0.14.dist-info/top_level.txt
odooku-11.0.14.dist-info/RECORD
