Metadata-Version: 2.1
Name: odooku
Version: 11.0.14
Summary: Odooku
Home-page: https://github.com/odooku/odooku
Author: Raymond Reggers - Adaptiv Design
Author-email: raymond@adaptiv.nl
License: Apache Software License
Platform: UNKNOWN
Classifier: Intended Audience :: Developers
Classifier: Operating System :: OS Independent
Classifier: Programming Language :: Python
Classifier: Programming Language :: Python :: 3
Classifier: Programming Language :: Python :: 3.5
Classifier: License :: OSI Approved :: Apache Software License
Requires-Python: >=3.5
Requires-Dist: boto3 (>=1.4.0)
Requires-Dist: click (>=6.6)
Requires-Dist: redis (>=2.10.5)
Requires-Dist: bpython (>=0.15.0)
Requires-Dist: gevent (>=1.2.2)
Requires-Dist: psycogreen (>=1.0)
Requires-Dist: gevent-websocket (>=0.10.1)
